clipboardjacker/__init__.py
clipboardjacker/clipboardjacker.py
clipboardjacker/main.py
clipboardjacker/version.py
clipboardjacker-0.1.4.dist-info/licenses/LICENSE
clipboardjacker-0.1.4.dist-info/METADATA
clipboardjacker-0.1.4.dist-info/WHEEL
clipboardjacker-0.1.4.dist-info/entry_points.txt
clipboardjacker-0.1.4.dist-info/top_level.txt
clipboardjacker-0.1.4.dist-info/RECORD
