Metadata-Version: 2.4
Name: clipboardjacker
Version: 0.1.4
Summary: A powerful Python tool for clipboard text replacement and monitoring
Home-page: https://github.com/ampedwastaken/ClipboardJacker
Author: AmpedWastaken
Author-email: ampedwastaken@gmail.com
Classifier: Programming Language :: Python :: 3
Classifier: License :: OSI Approved :: MIT License
Classifier: Operating System :: OS Independent
Classifier: Development Status :: 4 - Beta
Classifier: Intended Audience :: Developers
Classifier: Topic :: Security
Classifier: Topic :: Utilities
Requires-Python: >=3.8
License-File: LICENSE
Requires-Dist: pyperclip>=1.8.2
Dynamic: author
Dynamic: author-email
Dynamic: classifier
Dynamic: description
Dynamic: description-content-type
Dynamic: home-page
Dynamic: license-file
Dynamic: requires-dist
Dynamic: requires-python
Dynamic: summary
